[
  {
    "id": "WQY901",
    "name": "Vintage Shirt",
    "description": "Stay classy with this timeless striped Short Sleeve Patterned Vintage Shirt For Men. Perfect for a smart-casual look.",
    "price": 8999,
    "currency": "NGN",
    "categories": "Shirts",
    "brand": "Brand Name",
    "inventory": {
      "stock": 15,
      "availability": true
    },
    "images": "/assets/striped-polo.jpg"
  },

  {
    "id": "STCR702",
    "name": "Match Point Tennis Skirt",
    "description": "Grand Slam tournaments? Check! Olympic medals? Check! No. 1 golden girl Ash is our fitspo crush right now, so we're stealing her style with this super cute Match Point tennis skirt. Constructed with Eco Relay for a lightweight fit, freedom of movement and breathability, and featuring under short with side pockets, this is the perfect tennis companion! But why not take this number beyond the sidelines and wear it for running, team sports, or cheering on your fav player from the couch!",
    "price": 13999,
    "currency": "NGN",
    "categories": "Skirts",
    "brand": "Brand Name",
    "inventory": {
      "stock": 10,
      "availability": true
    },
    "images": "/assets/tennis-skirt.jpg"
  },

  {
    "id": "ABC123",
    "name": "Floral Shirt",
    "description": "This is a floral shirt that combines style and comfort. Perfect for any occasion.",
    "price": 9999,
    "currency": "NGN",
    "categories": "Shirt",
    "brand": "Brand Name",
    "inventory": {
      "stock": 0,
      "availability": false
    },
    "images": "/assets/floralShirt.jpg"
  },
  {
    "id": "DEF456",
    "name": "Denim Jeans",
    "description": "These denim jeans offer a classic look and a comfortable fit. A must-have for any wardrobe.",
    "price": 7999,
    "currency": "NGN",
    "categories": "Pants",
    "brand": "Brand Name",
    "inventory": {
      "stock": 20,
      "availability": true
    },
    "images": "/assets/denim.jpg"
  },
  {
    "id": "STC02",
    "name": "High Rise Tweed Mini Skirt ",
    "description": "This Women's High Rise Tweed Mini Skirt  is a versatile piece that can be dressed up or down.",
    "price": 12999,
    "currency": "NGN",
    "categories": "Skirts",
    "brand": "Brand Name",
    "inventory": {
      "stock": 10,
      "availability": true
    },
    "images": "/assets/high-rise-skirt.jpg"
  },
  {
    "id": "STC8702",
    "name": "Ladies Skirt",
    "description": "This pleated mini skirt is a versatile piece that can be dressed up or down.",
    "price": 27999,
    "currency": "NGN",
    "categories": "Skirts",
    "brand": "Brand Name",
    "inventory": {
      "stock": 10,
      "availability": true
    },
    "images": "/assets/ladies-skirt.jpg"
  },
  {
    "id": "GHI789",
    "name": "Leather Bag",
    "description": "This stylish leather bag is spacious and durable, making it ideal for everyday use.",
    "price": 14999,
    "currency": "NGN",
    "categories": "Bags",
    "brand": "Brand Name",
    "inventory": {
      "stock": 10,
      "availability": true
    },
    "images": "/assets/leatherbag.jpg"
  },
  {
    "id": "WXY701",
    "name": "Geometric Shirt",
    "description": "This bowling shirt features bright and colourful geometric motifs that recall the uniforms worn by horse riding jockeys. The collection is inspired by the Parade Ring, or paddock, where horses walk around as a warm-up before the race and to help racegoers pick a winner.",
    "price": 18999,
    "currency": "NGN",
    "categories": "Shirts",
    "brand": "Brand Name",
    "inventory": {
      "stock": 45,
      "availability": true
    },
    "images": "/assets/geaometric-shirt.jpg"
  },
  {
    "id": "JKL012",
    "name": "Striped Dress",
    "description": "This elegant striped dress is perfect for a night out or a special occasion. Stand out with style.",
    "price": 11999,
    "currency": "NGN",
    "categories": "Dresses",
    "brand": "Brand Name",
    "inventory": {
      "stock": 5,
      "availability": true
    },
    "images": "/assets/stripedress.jpg"
  },
  {
    "id": "MNO345",
    "name": "Graphic T-shirt",
    "description": "Express yourself with this cool and trendy graphic t-shirt. Make a statement wherever you go.",
    "price": 5999,
    "currency": "NGN",
    "categories": "Shirt",
    "brand": "Brand Name",
    "inventory": {
      "stock": 30,
      "availability": true
    },
    "images": "/assets/graphictshirt.jpg"
  },

  {
    "id": "VWX234",
    "name": "Classic Leather Belt",
    "description": "Add a touch of sophistication to your outfits with this classic leather belt.",
    "price": 4999,
    "currency": "NGN",
    "categories": "Accessories",
    "brand": "Brand Name",
    "inventory": {
      "stock": 25,
      "availability": true
    },
    "images": "/assets/leatherbelt.jpg"
  },
  {
    "id": "PQR678",
    "name": "Casual Sneakers",
    "description": "These casual sneakers offer both comfort and style. Perfect for everyday wear.",
    "price": 9999,
    "currency": "NGN",
    "categories": "Shoes",
    "brand": "Brand Name",
    "inventory": {
      "stock": 15,
      "availability": true
    },
    "images": "/assets/casualsneakers.jpg"
  },
  {
    "id": "STU901",
    "name": "Lace Evening Gown",
    "description": "This elegant lace evening gown is perfect for formal events and special occasions.",
    "price": 24999,
    "currency": "NGN",
    "categories": "Dresses",
    "brand": "Brand Name",
    "inventory": {
      "stock": 8,
      "availability": true
    },
    "images": "/assets/eveninggown.jpg"
  },

  {
    "id": "YZA567",
    "name": "Sports Cap",
    "description": "Stay cool and stylish with this comfortable sports cap. Perfect for outdoor activities.",
    "price": 2999,
    "currency": "NGN",
    "categories": "Accessories",
    "brand": "Brand Name",
    "inventory": {
      "stock": 12,
      "availability": true
    },
    "images": "/assets/sportscap.jpg"
  },

  {
    "id": "EFG123",
    "name": "Faux Leather Backpack",
    "description": "Carry your essentials in style with this trendy faux leather backpack. Perfect for daily use.",
    "price": 15999,
    "currency": "NGN",
    "categories": "Bags",
    "brand": "Brand Name",
    "inventory": {
      "stock": 7,
      "availability": true
    },
    "images": "/assets/bag.jpg"
  },
  {
    "id": "HIJ456",
    "name": "Printed Wrap Dress",
    "description": "Stay fashionable with this printed wrap dress. Perfect for both casual and formal occasions.",
    "price": 11999,
    "currency": "NGN",
    "categories": "Dresses",
    "brand": "Brand Name",
    "inventory": {
      "stock": 10,
      "availability": true
    },
    "images": "/assets/wrapdress.jpg"
  },
  {
    "id": "PAR678",
    "name": "Breathable Sneakers",
    "description": "These casual Sport Men's Breathable Running sneakers offer both comfort and style. Perfect for everyday wear.",
    "price": 8999,
    "currency": "NGN",
    "categories": "Shoes",
    "brand": "Brand Name",
    "inventory": {
      "stock": 15,
      "availability": true
    },
    "images": "/assets/breaheable.jpg"
  },
  {
    "id": "BCD890",
    "name": "Printed Maxi Skirt",
    "description": "Make a fashion statement with this vibrant printed maxi skirt. Perfect for summer vibes.",
    "price": 8999,
    "currency": "NGN",
    "categories": "Skirts",
    "brand": "Brand Name",
    "inventory": {
      "stock": 18,
      "availability": true
    },
    "images": "/assets/maxiskirt.jpg"
  },
  {
    "id": "EFG123",
    "name": "Gym & Travel Duffel Bag",
    "description": "Carry your essentials in style with this trendy Gym & Travel Duffel Bag. Perfect for daily use.",
    "price": 2599,
    "currency": "NGN",
    "categories": "Bags",
    "brand": "Brand Name",
    "inventory": {
      "stock": 7,
      "availability": true
    },
    "images": "/assets/gym-bag.jpg"
  },
  {
    "id": "TUV678",
    "name": "Leather Wallet",
    "description": "Keep your essentials organized with this stylish leather wallet. A must-have accessory.",
    "price": 4999,
    "currency": "NGN",
    "categories": "Accessories",
    "brand": "Brand Name",
    "inventory": {
      "stock": 25,
      "availability": true
    },
    "images": "/assets/leatherwallet.jpg"
  },
  {
    "id": "ZAB234",
    "name": "Bohemian Fringe Bag",
    "description": "Express your bohemian style with this unique fringe bag. Perfect for a boho-chic look.",
    "price": 15999,
    "currency": "NGN",
    "categories": "Bags",
    "brand": "Brand Name",
    "inventory": {
      "stock": 7,
      "availability": true
    },
    "images": "/assets/fringe-bag.jpg"
  },

  {
    "id": "HIJ123",
    "name": "Cotton Chinos",
    "description": "These comfortable cotton chinos are a versatile addition to your wardrobe.",
    "price": 7999,
    "currency": "NGN",
    "categories": "Pants",
    "brand": "Brand Name",
    "inventory": {
      "stock": 12,
      "availability": true
    },
    "images": "/assets/cotton-chinos.jpg"
  },

  {
    "id": "CDE567",
    "name": "Printed Kimono",
    "description": "Add a touch of exotic elegance to your wardrobe with this stunning printed kimono.",
    "price": 12999,
    "currency": "NGN",
    "categories": "Outerwear",
    "brand": "Brand Name",
    "inventory": {
      "stock": 10,
      "availability": true
    },
    "images": "/assets/kimono.jpg"
  },

  {
    "id": "KLM789",
    "name": "Designer Sunglasses",
    "description": "Protect your eyes and elevate your style with these chic designer sunglasses.",
    "price": 7999,
    "currency": "NGN",
    "categories": "Accessories",
    "brand": "Brand Name",
    "inventory": {
      "stock": 15,
      "availability": true
    },
    "images": "/assets/sunglass.jpg"
  },
  {
    "id": "NOP012",
    "name": "Printed Scarf",
    "description": "Add a touch of elegance to your outfit with this beautiful printed scarf.",
    "price": 3999,
    "currency": "NGN",
    "categories": "Accessories",
    "brand": "Brand Name",
    "inventory": {
      "stock": 20,
      "availability": true
    },
    "images": "/assets/scarf.jpg"
  },
  {
    "id": "QRS345",
    "name": "Ripped Denim Shorts",
    "description": "Stay trendy with these ripped denim shorts. Perfect for a casual and cool look.",
    "price": 6999,
    "currency": "NGN",
    "categories": "Shorts",
    "brand": "Brand Name",
    "inventory": {
      "stock": 8,
      "availability": true
    },
    "images": "/assets/ripped-denim-shorts.jpg"
  },

  {
    "id": "WXY901",
    "name": "Striped Polo Shirt",
    "description": "Stay classy with this timeless striped polo shirt. Perfect for a smart-casual look.",
    "price": 8999,
    "currency": "NGN",
    "categories": "Shirts",
    "brand": "Brand Name",
    "inventory": {
      "stock": 15,
      "availability": true
    },
    "images": "/assets/striped-polo.jpg"
  },
  {
    "id": "EFG890",
    "name": "Sleek Wristwatch",
    "description": "Stay punctual and stylish with this sleek and sophisticated wristwatch.",
    "price": 11999,
    "currency": "NGN",
    "categories": "Accessories",
    "brand": "Brand Name",
    "inventory": {
      "stock": 20,
      "availability": true
    },
    "images": "/assets/wristwatch.jpg"
  },
  {
    "id": "XYZ901",
    "name": "Tropical Print Maxi Dress",
    "description": "Capture the essence of summer with this vibrant tropical print maxi dress. Perfect for beach days and vacations.",
    "price": 17999,
    "currency": "NGN",
    "categories": "Dresses",
    "brand": "Brand Name",
    "inventory": {
      "stock": 8,
      "availability": true
    },
    "images": "/assets/dress.jpg"
  },
  {
    "id": "ABC234",
    "name": "Straw Beach Hat",
    "description": "Stay protected from the sun while looking stylish with this trendy straw beach hat.",
    "price": 4999,
    "currency": "NGN",
    "categories": "Accessories",
    "brand": "Brand Name",
    "inventory": {
      "stock": 15,
      "availability": true
    },
    "images": "/assets/straw-beach-hat.jpg"
  },
  {
    "id": "DEF567",
    "name": "Embroidered Denim Jacket",
    "description": "Upgrade your denim collection with this embroidered denim jacket. It adds a unique touch to any outfit.",
    "price": 15999,
    "currency": "NGN",
    "categories": "Jackets",
    "brand": "Brand Name",
    "inventory": {
      "stock": 10,
      "availability": true
    },
    "images": "/assets/denim-jacket.jpg"
  },
  {
    "id": "GHI890",
    "name": "Boho Fringe Earrings",
    "description": "Complete your boho look with these stylish fringe earrings. They add a free-spirited vibe to any ensemble.",
    "price": 5999,
    "currency": "NGN",
    "categories": "Accessories",
    "brand": "Brand Name",
    "inventory": {
      "stock": 20,
      "availability": true
    },
    "images": "/assets/fringe-earrings.jpg"
  },
  {
    "id": "JKL123",
    "name": "Printed Palazzo Pants",
    "description": "Make a statement with these printed palazzo pants. They offer a comfortable and fashionable look.",
    "price": 8999,
    "currency": "NGN",
    "categories": "Pants",
    "brand": "Brand Name",
    "inventory": {
      "stock": 12,
      "availability": true
    },
    "images": "/assets/printed-palazo-pants.jpg"
  },
  {
    "id": "STU902",
    "name": "Pleated Mini Skirt",
    "description": "This pleated mini skirt is a versatile piece that can be dressed up or down.",
    "price": 19999,
    "currency": "NGN",
    "categories": "Skirts",
    "brand": "Brand Name",
    "inventory": {
      "stock": 10,
      "availability": true
    },
    "images": "/assets/miniskirt.jpg"
  },
  {
    "id": "STU903",
    "name": "Ruffled Crop Top",
    "description": "This ruffled crop top is a trendy and flattering piece that is perfect for summer.",
    "price": 14999,
    "currency": "NGN",
    "categories": "Tops",
    "brand": "Brand Name",
    "inventory": {
      "stock": 6,
      "availability": true
    },
    "images": "/assets/crop-top.jpg"
  },
  {
    "id": "STU904",
    "name": "Vintage Denim Jacket",
    "description": "This vintage denim jacket is a classic piece that can be worn for years to come.",
    "price": 19999,
    "currency": "NGN",
    "categories": "Jackets",
    "brand": "Brand Name",
    "inventory": {
      "stock": 12,
      "availability": true
    },
    "images": "/assets/vintage-denim-jacket.jpg"
  },
  {
    "id": "STU905",
    "name": "Leather Leggings",
    "description": "These leather leggings are a must-have for any wardrobe. They are stylish and comfortable, and can be dressed up or down.",
    "price": 24999,
    "currency": "NGN",
    "categories": "Pants",
    "brand": "Brand Name",
    "inventory": {
      "stock": 4,
      "availability": true
    },
    "images": "/assets/leather-legging.jpg"
  },
  {
    "id": "STU906",
    "name": "Chunky Sneakers",
    "description": "These chunky sneakers are a trendy and comfortable pair of shoes that are perfect for everyday wear.",
    "price": 12999,
    "currency": "NGN",
    "categories": "Shoes",
    "brand": "Brand Name",
    "inventory": {
      "stock": 16,
      "availability": true
    },
    "images": "/assets/chunky-sneakers.jpg"
  },
  {
    "id": "STU907",
    "name": "Satchel Bag",
    "description": "This satchel bag is a stylish and functional bag that is perfect for everyday use.",
    "price": 14999,
    "currency": "NGN",
    "categories": "Bags",
    "brand": "Brand Name",
    "inventory": {
      "stock": 8,
      "availability": true
    },
    "images": "/assets/satchel-bag.jpg"
  },
  {
    "id": "STU950",
    "name": "Silk Pajamas",
    "description": "These silk pajamas are the perfect way to relax and unwind after a long day.",
    "price": 19999,
    "currency": "NGN",
    "categories": "Sleepwear",
    "brand": "Brand Name",
    "inventory": {
      "stock": 10,
      "availability": true
    },
    "images": "/assets/silk-pyjamas.jpg"
  },
  {
    "id": "STU951",
    "name": "Fleece Blanket",
    "description": "This fleece blanket is the perfect way to stay warm and cozy on a cold day.",
    "price": 14999,
    "currency": "NGN",
    "categories": "Home Decor",
    "brand": "Brand Name",
    "inventory": {
      "stock": 12,
      "availability": true
    },
    "images": "/assets/fleece-blanket.jpg"
  },
  {
    "id": "STU952",
    "name": "Coffee Mug",
    "description": "This coffee mug is the perfect way to start your day.",
    "price": 9999,
    "currency": "NGN",
    "categories": "Home Decor",
    "brand": "Brand Name",
    "inventory": {
      "stock": 8,
      "availability": true
    },
    "images": "/assets/coffee-mug.jpg"
  },
  {
    "id": "STU953",
    "name": "Planter",
    "description": "This planter is the perfect way to add a touch of greenery to your home.",
    "price": 12999,
    "currency": "NGN",
    "categories": "Home Decor",
    "brand": "Brand Name",
    "inventory": {
      "stock": 6,
      "availability": true
    },
    "images": "/assets/planter.jpg"
  },
  {
    "id": "STU954",
    "name": "Throw Pillow",
    "description": "This throw pillow is the perfect way to add a pop of color to your couch.",
    "price": 7999,
    "currency": "NGN",
    "categories": "Home Decor",
    "brand": "Brand Name",
    "inventory": {
      "stock": 10,
      "availability": true
    },
    "images": "/assets/throw-pillow.jpg"
  },
  {
    "id": "STU955",
    "name": "Nightstand",
    "description": "This nightstand is the perfect way to add storage and a touch of style to your bedroom.",
    "price": 24999,
    "currency": "NGN",
    "categories": "Home Decor",
    "brand": "Brand Name",
    "inventory": {
      "stock": 4,
      "availability": true
    },
    "images": "/assets/nightstand.jpg"
  }
]
